Metadata-Version: 2.4
Name: mseep-simplenote-mcp-server
Version: 1.4.2
Summary: A simple MCP Server that connects to Simplenote
Author: mseep
Author-email: mseep <support@skydeck.ai>
Maintainer: mseep
Maintainer-email: mseep <support@skydeck.ai>
License: MIT
Requires-Python: >=3.11
License-File: LICENSE
Requires-Dist: mcp[cli]>=0.4.0
Requires-Dist: simplenote>=2.1.4
Dynamic: author
Dynamic: license-file
Dynamic: maintainer
Dynamic: requires-python
